unico_device_setuper/__init__.py
unico_device_setuper/backend/__init__.py
unico_device_setuper/backend/app.py
unico_device_setuper/backend/app_maker.py
unico_device_setuper/backend/state.py
unico_device_setuper/backend/token.py
unico_device_setuper/backend/token_verifier.py
unico_device_setuper/backend/routes/__init__.py
unico_device_setuper/backend/routes/packages.py
unico_device_setuper/backend/routes/sygic_maps.py
unico_device_setuper/cli/__init__.py
unico_device_setuper/cli/logout.py
unico_device_setuper/cli/main.py
unico_device_setuper/cli/server.py
unico_device_setuper/cli/stp.py
unico_device_setuper/cli/command/__init__.py
unico_device_setuper/cli/command/ban_package.py
unico_device_setuper/cli/command/install_maps.py
unico_device_setuper/cli/command/install_uninav.py
unico_device_setuper/cli/command/publish_maps.py
unico_device_setuper/cli/command/register_sygic.py
unico_device_setuper/cli/command/register_unitech.py
unico_device_setuper/cli/command/unban_package.py
unico_device_setuper/cli/command/uninstall_packages.py
unico_device_setuper/lib/__init__.py
unico_device_setuper/lib/aapt.py
unico_device_setuper/lib/adb.py
unico_device_setuper/lib/aio.py
unico_device_setuper/lib/appium_settings.py
unico_device_setuper/lib/auth.py
unico_device_setuper/lib/cfg.py
unico_device_setuper/lib/cnsl.py
unico_device_setuper/lib/datadir.py
unico_device_setuper/lib/dl.py
unico_device_setuper/lib/env.py
unico_device_setuper/lib/oci.py
unico_device_setuper/lib/oci_object.py
unico_device_setuper/lib/openapi.py
unico_device_setuper/lib/pkg.py
unico_device_setuper/lib/rl.py
unico_device_setuper/lib/serde.py
unico_device_setuper/lib/socket.py
unico_device_setuper/lib/sygic.py
unico_device_setuper/lib/uninav.py
unico_device_setuper/lib/unitech_util.py
unico_device_setuper/lib/util.py
unico_device_setuper/lib/api/__init__.py
unico_device_setuper/lib/api/impl/__init__.py
unico_device_setuper/lib/api/impl/client.py
unico_device_setuper/lib/api/impl/errors.py
unico_device_setuper-1.16.12.dist-info/METADATA
unico_device_setuper-1.16.12.dist-info/WHEEL
unico_device_setuper-1.16.12.dist-info/entry_points.txt
unico_device_setuper-1.16.12.dist-info/RECORD
