Metadata-Version: 2.4
Name: unico_device_setuper
Version: 1.16.12
Author-email: Florian Daude <florian.daude@unicofrance.com>
Requires-Python: <3.13,>=3.12
Requires-Dist: attrs>=23.2.0
Requires-Dist: beautifulsoup4>=4.12.3
Requires-Dist: cyclopts>=2.9.9
Requires-Dist: email-validator>=2.2.0
Requires-Dist: fastapi>=0.111.0
Requires-Dist: gunicorn>=22.0.0
Requires-Dist: httpx>=0.27.0
Requires-Dist: keyring>=24.0.0
Requires-Dist: oci-client>=0.2.5
Requires-Dist: openpyxl>=3.1.3
Requires-Dist: platformdirs>=4.2.1
Requires-Dist: pydantic>=2.7.1
Requires-Dist: python-jose>=3.3.0
Requires-Dist: python-slugify>=8.0.4
Requires-Dist: slcfg>=0.3.1
Requires-Dist: tqdm>=4.66.4
Requires-Dist: typer>=0.12.3
Requires-Dist: uvicorn>=0.29.0
